plagcheck/__init__.py
plagcheck/analyze.py
plagcheck/plagcheck.py
plagcheck/plagcheck_test.py
plagcheck-0.4.dist-info/LICENSE
plagcheck-0.4.dist-info/METADATA
plagcheck-0.4.dist-info/WHEEL
plagcheck-0.4.dist-info/top_level.txt
plagcheck-0.4.dist-info/RECORD
