Metadata-Version: 2.1
Name: plagcheck
Version: 0.4
Summary: Moss Results scraper with powerful insights & analysis
Home-page: https://codeclassroom.github.io/PlagCheck/
Author: Bhupesh Varshney
Author-email: varshneybhupesh@gmail.com
License: MIT
Project-URL: Documentation, https://plagcheck.readthedocs.io/en/latest/?badge=latest
Project-URL: Source Code, https://github.com/codeclassroom/PlagCheck
Project-URL: Funding, https://www.patreon.com/bePatron?u=18082750
Project-URL: Say Thanks!, https://github.com/codeclassroom/PlagCheck/issues/new?assignees=&labels=&template=---say-thank-you.md&title=
Project-URL: Tracker, https://github.com/codeclassroom/PlagCheck/issues
Keywords: moss plagiarism analysis cheat mosspy
Platform: UNKNOWN
Classifier: Programming Language :: Python :: 3.6
Classifier: Programming Language :: Python :: 3.7
Classifier: Programming Language :: Python :: 3.8
Classifier: License :: OSI Approved :: MIT License
Classifier: Topic :: Software Development :: Build Tools
Classifier: Topic :: Education
Classifier: Topic :: Education
Classifier: Topic :: Software Development
Classifier: Topic :: Software Development :: Libraries
Classifier: Topic :: Software Development :: Libraries :: Python Modules
Classifier: Operating System :: OS Independent
Requires-Python: >=3.6
Requires-Dist: mosspy
Requires-Dist: beautifulsoup4
Requires-Dist: lxml
